.travis.yml
CHANGES.rst
COPYRIGHT.txt
LICENSE.txt
MANIFEST.in
README.rst
bootstrap.py
buildout.cfg
setup.py
src/zc/__init__.py
src/zc.ngi.egg-info/PKG-INFO
src/zc.ngi.egg-info/SOURCES.txt
src/zc.ngi.egg-info/dependency_links.txt
src/zc.ngi.egg-info/namespace_packages.txt
src/zc.ngi.egg-info/not-zip-safe
src/zc.ngi.egg-info/requires.txt
src/zc.ngi.egg-info/top_level.txt
src/zc/ngi/__init__.py
src/zc/ngi/adapters.py
src/zc/ngi/adapters.test
src/zc/ngi/async-udp.test
src/zc/ngi/async.py
src/zc/ngi/async.test
src/zc/ngi/blocking.py
src/zc/ngi/blocking.test
src/zc/ngi/generator.py
src/zc/ngi/interfaces.py
src/zc/ngi/message.py
src/zc/ngi/message.test
src/zc/ngi/old.test
src/zc/ngi/testing.py
src/zc/ngi/testing.test
src/zc/ngi/tests.py
src/zc/ngi/wordcount.py
src/zc/ngi/doc/Makefile
src/zc/ngi/doc/conf.py
src/zc/ngi/doc/contents.txt
src/zc/ngi/doc/echo_server.py
src/zc/ngi/doc/index.txt
src/zc/ngi/doc/reference.txt