Metadata-Version: 1.1
Name: zc.ngi
Version: 2.1.0
Summary: Network Gateway Interface
Home-page: http://packages.python.org/zc.ngi
Author: Jim Fulton
Author-email: jim@zope.com
License: ZPL 2.1
Keywords: networking,testing
Platform: UNKNOWN
Classifier: Intended Audience :: Developers
Classifier: License :: OSI Approved :: MIT License
Classifier: Programming Language :: Python
Classifier: Programming Language :: Python :: 2
Classifier: Programming Language :: Python :: 2.7
Classifier: Programming Language :: Python :: Implementation :: CPython
